{
  "name" : "Woktype",
  "originTableName" : "woktype",
  "comment" : null,
  "fullColumn" : [ {
    "name" : "worktypeid",
    "comment" : null,
    "type" : null,
    "shortType" : null,
    "ktShortType" : "Int",
    "custom" : false,
    "ext" : { }
  }, {
    "name" : "workname",
    "comment" : null,
    "type" : null,
    "shortType" : null,
    "ktShortType" : "String",
    "custom" : false,
    "ext" : { }
  } ],
  "pkColumn" : null,
  "otherColumn" : null,
  "savePackageName" : "com.zy",
  "savePath" : "./src/main/java/com/zy",
  "saveModelName" : "wiyebaoxiu"
}